odoo/addons/web_company_logo/README.rst
odoo/addons/web_company_logo/__init__.py
odoo/addons/web_company_logo/__manifest__.py
odoo/addons/web_company_logo/controllers/__init__.py
odoo/addons/web_company_logo/controllers/main.py
odoo/addons/web_company_logo/static/description/icon.png
odoo/addons/web_company_logo/static/src/css/menu.css
odoo/addons/web_company_logo/static/src/js/menu.js
odoo/addons/web_company_logo/static/src/xml/menu.xml
odoo/addons/web_company_logo/templates/assets.xml
odoo14_addon_web_company_logo-14.0.1.0.0.dist-info/METADATA
odoo14_addon_web_company_logo-14.0.1.0.0.dist-info/WHEEL
odoo14_addon_web_company_logo-14.0.1.0.0.dist-info/top_level.txt
odoo14_addon_web_company_logo-14.0.1.0.0.dist-info/RECORD
