Metadata-Version: 2.1
Name: odoo14-addon-web_company_logo
Version: 14.0.1.0.0
Summary: Web Company Logo
Home-page: https://www.kareemabuzaid.com, https://www.sygel.es
Author: Kareem Abuzaid, kareem.abuzaid123@gmail.com, Sygel
License: AGPL-3
Classifier: Programming Language :: Python
Classifier: Framework :: Odoo
Classifier: Framework :: Odoo :: 14.0
Classifier: License :: OSI Approved :: GNU Affero General Public License v3
Requires-Python: >=3.6
Requires-Dist: odoo<14.1dev,>=14.0a
